mitsubishi_plc/__init__.py
mitsubishi_plc/exception.py
mitsubishi_plc/mitsubishi_plc.py
mitsubishi_plc-1.6.0.dist-info/METADATA
mitsubishi_plc-1.6.0.dist-info/WHEEL
mitsubishi_plc-1.6.0.dist-info/RECORD
