Metadata-Version: 2.4
Name: mitsubishi-plc
Version: 1.6.0
Summary: 
Author: LiuWei
Author-email: 183074632@qq.com
Requires-Python: >=3.11,<4.0
Classifier: Programming Language :: Python :: 3
Classifier: Programming Language :: Python :: 3.11
Classifier: Programming Language :: Python :: 3.12
Classifier: Programming Language :: Python :: 3.13
Classifier: Programming Language :: Python :: 3.14
Requires-Dist: hslcommunication (>=1.2.0,<2.0.0)
